tagcloser/__init__.py
tagcloser-1.3.0.dist-info/DESCRIPTION.rst
tagcloser-1.3.0.dist-info/METADATA
tagcloser-1.3.0.dist-info/RECORD
tagcloser-1.3.0.dist-info/WHEEL
tagcloser-1.3.0.dist-info/metadata.json
tagcloser-1.3.0.dist-info/top_level.txt
