Metadata-Version: 2.0
Name: tagcloser
Version: 1.3.0
Summary: This is to close unclosed html tag in html file, mainly for generating the excerpt html.
Home-page: https://github.com/Hao-Luo/TagCloser
Author: Hao Luo
Author-email: hao@sporule.com
License: GPL
Keywords: html htmltag excerpt
Platform: UNKNOWN
